mindthegap/__init__.py
mindthegap/passwordmanagerclass.py
python_local_passwords-0.0.2.dist-info/METADATA
python_local_passwords-0.0.2.dist-info/WHEEL
python_local_passwords-0.0.2.dist-info/top_level.txt
python_local_passwords-0.0.2.dist-info/RECORD
