Metadata-Version: 2.1
Name: python-local-passwords
Version: 0.0.2
Summary: A package for key generation, encrypting and decrypting passwords
Home-page: UNKNOWN
Author: dave_the_noob
Author-email: dave.dawson86@gmail.com
License: UNKNOWN
Keywords: python,encryption,passwords,decrypting,key generation
Platform: UNKNOWN
Classifier: Development Status :: 1 - Planning
Classifier: Intended Audience :: Developers
Classifier: Programming Language :: Python :: 3
Classifier: Operating System :: Unix
Classifier: Operating System :: MacOS :: MacOS X
Classifier: Operating System :: Microsoft :: Windows
Requires-Dist: typing
Requires-Dist: cryptography
